django_scotty/__init__.py
django_scotty/apps.py
django_scotty/helpers.py
django_scotty/templates/cotton/django_simple_table.html
django_scotty/templates/django_tables2/base_django_tables2.html
django_scotty/templates/django_tables2/base_django_tables2_dict.html
django_scotty/templates/django_tables2/django_tables_filter_line.html
django_scotty/templates/django_tables2/dummy.html
django_scotty/templates/django_tables2/generic_detail.html
django_scotty/templates/django_tables2/rioja_table_template.html
django_scotty/templates/django_tables2/rioja_table_template_dict.html
django_scotty/templatetags/sluguer.py
django_scotty-0.1.3.dist-info/WHEEL
django_scotty-0.1.3.dist-info/METADATA
django_scotty-0.1.3.dist-info/RECORD
