Metadata-Version: 2.3
Name: django-scotty
Version: 0.1.3
Summary: Advanced tables for django cruds
Author: Juan Manuel Schillaci
Author-email: Juan Manuel Schillaci <jmschillaci@gmail.com>
Requires-Dist: django-cotton>=2.1.3
Requires-Dist: django-crispy-forms>=2.4
Requires-Dist: django-filter>=25.2
Requires-Dist: django-htmx>=1.26.0
Requires-Dist: django-tables2>=2.7.5
Requires-Dist: tablib>=3.8.0
Requires-Python: >=3.12
